Workbook

Sheet data_export
A1: program_label_short | B1: transfer | C1: wtp_env | D1: env_cost_wtp | E1: cost_wtp | F1: producers | G1: WTP | H1: fisc_tot | I1: cost | J1: MVPF
A2: Wind Production Credits | B2: 1 | C2: 4.24778 | D2: 1.900318 | E2: 0.6449316 | F2: 0 | G2: 7.79303 | H2: 0.3276403 | I2: 1.32764 | J2: 5.869835
A3: PTC (Shrimali) | B3: 1 | C3: 5.325597 | D3: 3.276529 | E3: 0.919621 | F3: 0 | G3: 10.52175 | H3: 0.3942201 | I3: 1.39422 | J3: 7.54669
A4: PTC (Metcalf) | B4: 1 | C4: 3.966325 | D4: 1.426829 | E4: 0.5598809 | F4: 0 | G4: 6.953035 | H4: 0.3123734 | I4: 1.312373 | J4: 5.298061
A5: PTC (Hitaj) | B5: 1 | C5: 3.451419 | D5: 0.9975948 | E5: 0.4552929 | F5: 0 | G5: 5.904307 | H5: 0.2763275 | I5: 1.276327 | J5: 4.626013
A6: Residential Solar | B6: 1.1056 | C6: 1.548539 | D6: 2.279867 | E6: 1.635643 | F6: -0.2137665 | G6: 6.355883 | H6: 0.6458964 | I6: 1.645896 | J6: 3.861654
A7: CSI | B7: 1 | C7: 3.875875 | D7: 4.987633 | E7: 3.98739 | F7: -0.5350411 | G7: 13.31586 | H7: 1.629892 | I7: 2.629892 | J7: 5.063271
A8: NE Solar | B8: 1 | C8: 1.099671 | D8: 3.132328 | E8: 1.609878 | F8: -0.1518029 | G8: 6.690074 | H8: 0.4307094 | I8: 1.430709 | J8: 4.676054
A9: CSI (TPO) | B9: 1.528 | C9: 1.446457 | D9: 1.982251 | E9: 1.371067 | F9: -0.1996747 | G9: 6.128101 | H9: 0.6061215 | I9: 1.606121 | J9: 3.815466
A10: CSI (HO) | B10: 1 | C10: 0.8401305 | D10: 1.081114 | E10: 0.8643025 | F10: -0.1159749 | G10: 3.669572 | H10: 0.3532937 | I10: 1.353294 | J10: 2.711586
A11: CT Solar | B11: 1 | C11: 0.4805634 | D11: 0.2160097 | E11: 0.3455759 | F11: -0.0663389 | G11: 1.97581 | H11: 0.2094654 | I11: 1.209465 | J11: 1.633623
A12: Electric Vehicles | B12: 1 | C12: 0.0889978 | D12: 0.0733491 | E12: 0.4516476 | F12: -0.0427899 | G12: 1.571205 | H12: 0.0871514 | I12: 1.087151 | J12: 1.445249
A13: BEV (State - Rebate) | B13: 1 | C13: 0.1067966 | D13: 0.1027134 | E13: 0.5637379 | F13: -0.0513475 | G13: 1.7219 | H13: 0.1028943 | I13: 1.102894 | J13: 1.561256
... A92: WAP (Mexico) | B92: 0.5 | C92: -0.0775422 | D92: 0 | E92: 0 | F92: 0 | G92: 0.4224578 | H92: 0.0015143 | I92: 1.001514 | J92: 0.421819

Sheet TABLE
J8: Willingness to Pay | R8: Cost
M10: Learning by Doing
F11: Panel A. Subsidies | J11: Transfer | K11: Env. Benefits | M11: Env. | N11: Price | O11: Profits | P11: WTP | R11: Fiscal Externality | S11: Total | T11: MVPF
G13: =data_export!A2 -> Wind Production Credits | J13: =IF(data_export!B2=0, "", data_export!B2) -> 1 | K13: =IF(data_export!C2=0, "", data_export!C2) -> 4.24778 | M13: =IF(data_export!D2=0, "", data_export!D2) -> 1.900318 | N13: =IF(data_export!E2=0, "", data_export!E2) -> 0.6449316 | O13: =IF(data_export!F2=0, "", data_export!F2) | P13: =IF(data_export!G2=0, "", data_export!G2) -> 7.79303 | R13: =IF(data_export!H2=0, "", data_export!H2) -> 0.3276403 | S13: =IF(data_export!I2=0, "", data_export!I2) -> 1.32764 | T13: =IF(data_export!J2=0, "", data_export!J2) -> 5.869835
H14: =data_export!A3 -> PTC (Shrimali) | J14: =IF(data_export!B3=0, "", data_export!B3) -> 1 | K14: =IF(data_export!C3=0, "", data_export!C3) -> 5.325597 | M14: =IF(data_export!D3=0, "", data_export!D3) -> 3.276529 | N14: =IF(data_export!E3=0, "", data_export!E3) -> 0.919621 | O14: =IF(data_export!F3=0, "", data_export!F3) | P14: =IF(data_export!G3=0, "", data_export!G3) -> 10.52175 | R14: =IF(data_export!H3=0, "", data_export!H3) -> 0.3942201 | S14: =IF(data_export!I3=0, "", data_export!I3) -> 1.39422 | T14: =IF(data_export!J3=0, "", data_export!J3) -> 7.54669
H15: =data_export!A4 -> PTC (Metcalf) | J15: =IF(data_export!B4=0, "", data_export!B4) -> 1 | K15: =IF(data_export!C4=0, "", data_export!C4) -> 3.966325 | M15: =IF(data_export!D4=0, "", data_export!D4) -> 1.426829 | N15: =IF(data_export!E4=0, "", data_export!E4) -> 0.5598809 | O15: =IF(data_export!F4=0, "", data_export!F4) | P15: =IF(data_export!G4=0, "", data_export!G4) -> 6.953035 | R15: =IF(data_export!H4=0, "", data_export!H4) -> 0.3123734 | S15: =IF(data_export!I4=0, "", data_export!I4) -> 1.312373 | T15: =IF(data_export!J4=0, "", data_export!J4) -> 5.298061
H16: =data_export!A5 -> PTC (Hitaj) | J16: =IF(data_export!B5=0, "", data_export!B5) -> 1 | K16: =IF(data_export!C5=0, "", data_export!C5) -> 3.451419 | M16: =IF(data_export!D5=0, "", data_export!D5) -> 0.9975948 | N16: =IF(data_export!E5=0, "", data_export!E5) -> 0.4552929 | O16: =IF(data_export!F5=0, "", data_export!F5) | P16: =IF(data_export!G5=0, "", data_export!G5) -> 5.904307 | R16: =IF(data_export!H5=0, "", data_export!H5) -> 0.2763275 | S16: =IF(data_export!I5=0, "", data_export!I5) -> 1.276327 | T16: =IF(data_export!J5=0, "", data_export!J5) -> 4.626013
H18: =data_export!A6 -> Residential Solar | J18: =IF(data_export!B6=0, "", data_export!B6) -> 1.1056 | K18: =IF(data_export!C6=0, "", data_export!C6) -> 1.548539 | M18: =IF(data_export!D6=0, "", data_export!D6) -> 2.279867 | N18: =IF(data_export!E6=0, "", data_export!E6) -> 1.635643 | O18: =IF(data_export!F6=0, "", data_export!F6) -> -0.2137665 | P18: =IF(data_export!G6=0, "", data_export!G6) -> 6.355883 | R18: =IF(data_export!H6=0, "", data_export!H6) -> 0.6458964 | S18: =IF(data_export!I6=0, "", data_export!I6) -> 1.645896 | T18: =IF(data_export!J6=0, "", data_export!J6) -> 3.861654
H19: =data_export!A7 -> CSI | J19: =IF(data_export!B7=0, "", data_export!B7) -> 1 | K19: =IF(data_export!C7=0, "", data_export!C7) -> 3.875875 | M19: =IF(data_export!D7=0, "", data_export!D7) -> 4.987633 | N19: =IF(data_export!E7=0, "", data_export!E7) -> 3.98739 | O19: =IF(data_export!F7=0, "", data_export!F7) -> -0.5350411 | P19: =IF(data_export!G7=0, "", data_export!G7) -> 13.31586 | R19: =IF(data_export!H7=0, "", data_export!H7) -> 1.629892 | S19: =IF(data_export!I7=0, "", data_export!I7) -> 2.629892 | T19: =IF(data_export!J7=0, "", data_export!J7) -> 5.063271
H20: =data_export!A8 -> NE Solar | J20: =IF(data_export!B8=0, "", data_export!B8) -> 1 | K20: =IF(data_export!C8=0, "", data_export!C8) -> 1.099671 | M20: =IF(data_export!D8=0, "", data_export!D8) -> 3.132328 | N20: =IF(data_export!E8=0, "", data_export!E8) -> 1.609878 | O20: =IF(data_export!F8=0, "", data_export!F8) -> -0.1518029 | P20: =IF(data_export!G8=0, "", data_export!G8) -> 6.690074 | R20: =IF(data_export!H8=0, "", data_export!H8) -> 0.4307094 | S20: =IF(data_export!I8=0, "", data_export!I8) -> 1.430709 | T20: =IF(data_export!J8=0, "", data_export!J8) -> 4.676054
H21: =data_export!A9 -> CSI (TPO) | J21: =IF(data_export!B9=0, "", data_export!B9) -> 1.528 | K21: =IF(data_export!C9=0, "", data_export!C9) -> 1.446457 | M21: =IF(data_export!D9=0, "", data_export!D9) -> 1.982251 | N21: =IF(data_export!E9=0, "", data_export!E9) -> 1.371067 | O21: =IF(data_export!F9=0, "", data_export!F9) -> -0.1996747 | P21: =IF(data_export!G9=0, "", data_export!G9) -> 6.128101 | R21: =IF(data_export!H9=0, "", data_export!H9) -> 0.6061215 | S21: =IF(data_export!I9=0, "", data_export!I9) -> 1.606121 | T21: =IF(data_export!J9=0, "", data_export!J9) -> 3.815466
H22: =data_export!A10 -> CSI (HO) | J22: =IF(data_export!B10=0, "", data_export!B10) -> 1 | K22: =IF(data_export!C10=0, "", data_export!C10) -> 0.8401305 | M22: =IF(data_export!D10=0, "", data_export!D10) -> 1.081114 | N22: =IF(data_export!E10=0, "", data_export!E10) -> 0.8643025 | O22: =IF(data_export!F10=0, "", data_export!F10) -> -0.1159749 | P22: =IF(data_export!G10=0, "", data_export!G10) -> 3.669572 | R22: =IF(data_export!H10=0, "", data_export!H10) -> 0.3532937 | S22: =IF(data_export!I10=0, "", data_export!I10) -> 1.353294 | T22: =IF(data_export!J10=0, "", data_export!J10) -> 2.711586
H23: =data_export!A11 -> CT Solar | J23: =IF(data_export!B11=0, "", data_export!B11) -> 1 | K23: =IF(data_export!C11=0, "", data_export!C11) -> 0.4805634 | M23: =IF(data_export!D11=0, "", data_export!D11) -> 0.2160097 | N23: =IF(data_export!E11=0, "", data_export!E11) -> 0.3455759 | O23: =IF(data_export!F11=0, "", data_export!F11) -> -0.0663389 | P23: =IF(data_export!G11=0, "", data_export!G11) -> 1.97581 | R23: =IF(data_export!H11=0, "", data_export!H11) -> 0.2094654 | S23: =IF(data_export!I11=0, "", data_export!I11) -> 1.209465 | T23: =IF(data_export!J11=0, "", data_export!J11) -> 1.633623
G25: =data_export!A12 -> Electric Vehicles | J25: =IF(data_export!B12=0, "", data_export!B12) -> 1 | K25: =IF(data_export!C12=0, "", data_export!C12) -> 0.0889978 | M25: =IF(data_export!D12=0, "", data_export!D12) -> 0.0733491 | N25: =IF(data_export!E12=0, "", data_export!E12) -> 0.4516476 | O25: =IF(data_export!F12=0, "", data_export!F12) -> -0.0427899 | P25: =IF(data_export!G12=0, "", data_export!G12) -> 1.571205 | R25: =IF(data_export!H12=0, "", data_export!H12) -> 0.0871514 | S25: =IF(data_export!I12=0, "", data_export!I12) -> 1.087151 | T25: =IF(data_export!J12=0, "", data_export!J12) -> 1.445249
H26: =data_export!A13 -> BEV (State - Rebate) | J26: =IF(data_export!B13=0, "", data_export!B13) -> 1 | K26: =IF(data_export!C13=0, "", data_export!C13) -> 0.1067966 | M26: =IF(data_export!D13=0, "", data_export!D13) -> 0.1027134 | N26: =IF(data_export!E13=0, "", data_export!E13) -> 0.5637379 | O26: =IF(data_export!F13=0, "", data_export!F13) -> -0.0513475 | P26: =IF(data_export!G13=0, "", data_export!G13) -> 1.7219 | R26: =IF(data_export!H13=0, "", data_export!H13) -> 0.1028943 | S26: =IF(data_export!I13=0, "", data_export!I13) -> 1.102894 | T26: =IF(data_export!J13=0, "", data_export!J13) -> 1.561256
H27: =data_export!A14 -> ITC (EV) | J27: =IF(data_export!B14=0, "", data_export!B14) -> 1 | K27: =IF(data_export!C14=0, "", data_export!C14) -> 0.0951507 | M27: =IF(data_export!D14=0, "", data_export!D14) -> 0.0777018 | N27: =IF(data_export!E14=0, "", data_export!E14) -> 0.4820471 | O27: =IF(data_export!F14=0, "", data_export!F14) -> -0.0457482 | P27: =IF(data_export!G14=0, "", data_export!G14) -> 1.609151 | R27: =IF(data_export!H14=0, "", data_export!H14) -> 0.0919185 | S27: =IF(data_export!I14=0, "", data_export!I14) -> 1.091918 | T27: =IF(data_export!J14=0, "", data_export!J14) -> 1.473692
H28: =data_export!A15 -> EFMP | J28: =IF(data_export!B15=0, "", data_export!B15) -> 1 | K28: =IF(data_export!C15=0, "", data_export!C15) -> 0.0650462 | M28: =IF(data_export!D15=0, "", data_export!D15) -> 0.0396321 | N28: =IF(data_export!E15=0, "", data_export!E15) -> 0.3091578 | O28: =IF(data_export!F15=0, "", data_export!F15) -> -0.0312741 | P28: =IF(data_export!G15=0, "", data_export!G15) -> 1.382562 | R28: =IF(data_export!H15=0, "", data_export!H15) -> 0.0666414 | S28: =IF(data_export!I15=0, "", data_export!I15) -> 1.066641 | T28: =IF(data_export!J15=0, "", data_export!J15) -> 1.296183
G30: =data_export!A16 -> Appliance Rebates | J30: =IF(data_export!B16=0, "", data_export!B16) -> 0.8674783 | K30: =IF(data_export!C16=0, "", data_export!C16) -> 0.4506499 | M30: =IF(data_export!D16=0, "", data_export!D16) | N30: =IF(data_export!E16=0, "", data_export!E16) | O30: =IF(data_export!F16=0, "", data_export!F16) -> -0.1031324 | P30: =IF(data_export!G16=0, "", data_export!G16) -> 1.214996 | R30: =IF(data_export!H16=0, "", data_export!H16) -> 0.0435868 | S30: =IF(data_export!I16=0, "", data_export!I16) -> 1.043587 | T30: =IF(data_export!J16=0, "", data_export!J16) -> 1.16425
H31: =data_export!A17 -> C4A (CW) | J31: =IF(data_export!B17=0, "", data_export!B17) -> 0.9525 | K31: =IF(data_export!C17=0, "", data_export!C17) -> 0.5088034 | M31: =IF(data_export!D17=0, "", data_export!D17) | N31: =IF(data_export!E17=0, "", data_export!E17) | O31: =IF(data_export!F17=0, "", data_export!F17) -> -0.0387521 | P31: =IF(data_export!G17=0, "", data_export!G17) -> 1.422551 | R31: =IF(data_export!H17=0, "", data_export!H17) -> 0.0124157 | S31: =IF(data_export!I17=0, "", data_export!I17) -> 1.012416 | T31: =IF(data_export!J17=0, "", data_export!J17) -> 1.405106
H32: =data_export!A18 -> ES (WH) | J32: =IF(data_export!B18=0, "", data_export!B18) -> 0.5978261 | K32: =IF(data_export!C18=0, "", data_export!C18) -> 1.505917 | M32: =IF(data_export!D18=0, "", data_export!D18) | N32: =IF(data_export!E18=0, "", data_export!E18) | O32: =IF(data_export!F18=0, "", data_export!F18) -> -0.6586787 | P32: =IF(data_export!G18=0, "", data_export!G18) -> 1.445065 | R32: =IF(data_export!H18=0, "", data_export!H18) -> 0.0783753 | S32: =IF(data_export!I18=0, "", data_export!I18) -> 1.078375 | T32: =IF(data_export!J18=0, "", data_export!J18) -> 1.340039
H33: =data_export!A19 -> ES (CW) | J33: =IF(data_export!B19=0, "", data_export!B19) -> 1 | K33: =IF(data_export!C19=0, "", data_export!C19) -> 0.7938316 | M33: =IF(data_export!D19=0, "", data_export!D19) | N33: =IF(data_export!E19=0, "", data_export!E19) | O33: =IF(data_export!F19=0, "", data_export!F19) -> -0.0718637 | P33: =IF(data_export!G19=0, "", data_export!G19) -> 1.721968 | R33: =IF(data_export!H19=0, "", data_export!H19) -> 0.314836 | S33: =IF(data_export!I19=0, "", data_export!I19) -> 1.314836 | T33: =IF(data_export!J19=0, "", data_export!J19) -> 1.309645
H34: =data_export!A20 -> C4A (DW) | J34: =IF(data_export!B20=0, "", data_export!B20) -> 0.9295 | K34: =IF(data_export!C20=0, "", data_export!C20) -> 0.2253946 | M34: =IF(data_export!D20=0, "", data_export!D20) | N34: =IF(data_export!E20=0, "", data_export!E20) | O34: =IF(data_export!F20=0, "", data_export!F20) -> -0.0166163 | P34: =IF(data_export!G20=0, "", data_export!G20) -> 1.138278 | R34: =IF(data_export!H20=0, "", data_export!H20) -> 0.0052036 | S34: =IF(data_export!I20=0, "", data_export!I20) -> 1.005204 | T34: =IF(data_export!J20=0, "", data_export!J20) -> 1.132386
H35: =data_export!A21 -> ES (DW) | J35: =IF(data_export!B21=0, "", data_export!B21) -> 1 | K35: =IF(data_export!C21=0, "", data_export!C21) -> -0.2053294 | M35: =IF(data_export!D21=0, "", data_export!D21) | N35: =IF(data_export!E21=0, "", data_export!E21) | O35: =IF(data_export!F21=0, "", data_export!F21) -> 0.018588 | P35: =IF(data_export!G21=0, "", data_export!G21) -> 0.8132586 | R35: =IF(data_export!H21=0, "", data_export!H21) -> -0.2279527 | S35: =IF(data_export!I21=0, "", data_export!I21) -> 0.7720473 | T35: =IF(data_export!J21=0, "", data_export!J21) -> 1.053379
H36: =data_export!A22 -> C4A (Fridge) | J36: =IF(data_export!B22=0, "", data_export!B22) -> 0.9599999 | K36: =IF(data_export!C22=0, "", data_export!C22) -> 0.0914723 | M36: =IF(data_export!D22=0, "", data_export!D22) | N36: =IF(data_export!E22=0, "", data_export!E22) | O36: =IF(data_export!F22=0, "", data_export!F22) -> -0.0071807 | P36: =IF(data_export!G22=0, "", data_export!G22) -> 1.044292 | R36: =IF(data_export!H22=0, "", data_export!H22) -> 0.0023472 | S36: =IF(data_export!I22=0, "", data_export!I22) -> 1.002347 | T36: =IF(data_export!J22=0, "", data_export!J22) -> 1.041846
H37: =data_export!A23 -> ES (Fridge) | J37: =IF(data_export!B23=0, "", data_export!B23) -> 1 | K37: =IF(data_export!C23=0, "", data_export!C23) -> 0.1832727 | M37: =IF(data_export!D23=0, "", data_export!D23) | N37: =IF(data_export!E23=0, "", data_export!E23) | O37: =IF(data_export!F23=0, "", data_export!F23) -> -0.0165912 | P37: =IF(data_export!G23=0, "", data_export!G23) -> 1.166681 | R37: =IF(data_export!H23=0, "", data_export!H23) -> 0.1535091 | S37: =IF(data_export!I23=0, "", data_export!I23) -> 1.153509 | T37: =IF(data_export!J23=0, "", data_export!J23) -> 1.011419
H38: =data_export!A24 -> CA ESA | J38: =IF(data_export!B24=0, "", data_export!B24) -> 0.5 | K38: =IF(data_export!C24=0, "", data_export!C24) -> 0.5018364 | M38: =IF(data_export!D24=0, "", data_export!D24) | N38: =IF(data_export!E24=0, "", data_export!E24) | O38: =IF(data_export!F24=0, "", data_export!F24) -> -0.0339649 | P38: =IF(data_export!G24=0, "", data_export!G24) -> 0.9678716 | R38: =IF(data_export!H24=0, "", data_export!H24) -> 0.00996 | S38: =IF(data_export!I24=0, "", data_export!I24) -> 1.00996 | T38: =IF(data_export!J24=0, "", data_export!J24) -> 0.9583266
G40: =data_export!A25 -> Vehicle Retirement | J40: =IF(data_export!B25=0, "", data_export!B25) -> 0.9101124 | K40: =IF(data_export!C25=0, "", data_export!C25) -> 0.24524 | M40: =IF(data_export!D25=0, "", data_export!D25) | N40: =IF(data_export!E25=0, "", data_export!E25) | O40: =IF(data_export!F25=0, "", data_export!F25) -> -0.0492736 | P40: =IF(data_export!G25=0, "", data_export!G25) -> 1.106079 | R40: =IF(data_export!H25=0, "", data_export!H25) -> 0.0559767 | S40: =IF(data_export!I25=0, "", data_export!I25) -> 1.055977 | T40: =IF(data_export!J25=0, "", data_export!J25) -> 1.047446
H41: =data_export!A26 -> C4C (TX) | J41: =IF(data_export!B26=0, "", data_export!B26) -> 1 | K41: =IF(data_export!C26=0, "", data_export!C26) -> 0.2313007 | M41: =IF(data_export!D26=0, "", data_export!D26) | N41: =IF(data_export!E26=0, "", data_export!E26) | O41: =IF(data_export!F26=0, "", data_export!F26) -> -0.0740984 | P41: =IF(data_export!G26=0, "", data_export!G26) -> 1.157202 | R41: =IF(data_export!H26=0, "", data_export!H26) -> 0.0844116 | S41: =IF(data_export!I26=0, "", data_export!I26) -> 1.084412 | T41: =IF(data_export!J26=0, "", data_export!J26) -> 1.067125
H42: =data_export!A27 -> C4C (US) | J42: =IF(data_export!B27=0, "", data_export!B27) -> 1 | K42: =IF(data_export!C27=0, "", data_export!C27) -> 0.1507279 | M42: =IF(data_export!D27=0, "", data_export!D27) | N42: =IF(data_export!E27=0, "", data_export!E27) | O42: =IF(data_export!F27=0, "", data_export!F27) -> -0.0486073 | P42: =IF(data_export!G27=0, "", data_export!G27) -> 1.102121 | R42: =IF(data_export!H27=0, "", data_export!H27) -> 0.0553809 | S42: =IF(data_export!I27=0, "", data_export!I27) -> 1.055381 | T42: =IF(data_export!J27=0, "", data_export!J27) -> 1.044287
H43: =data_export!A28 -> BAAQMD | J43: =IF(data_export!B28=0, "", data_export!B28) -> 0.7303371 | K43: =IF(data_export!C28=0, "", data_export!C28) -> 0.3536914 | M43: =IF(data_export!D28=0, "", data_export!D28) | N43: =IF(data_export!E28=0, "", data_export!E28) | O43: =IF(data_export!F28=0, "", data_export!F28) -> -0.0251152 | P43: =IF(data_export!G28=0, "", data_export!G28) -> 1.058913 | R43: =IF(data_export!H28=0, "", data_export!H28) -> 0.0281376 | S43: =IF(data_export!I28=0, "", data_export!I28) -> 1.028138 | T43: =IF(data_export!J28=0, "", data_export!J28) -> 1.029933
G45: =data_export!A29 -> Hybrid Vehicles | J45: =IF(data_export!B29=0, "", data_export!B29) -> 1 | K45: =IF(data_export!C29=0, "", data_export!C29) -> 0.0081383 | M45: =IF(data_export!D29=0, "", data_export!D29) -> 0.0003883 | N45: =IF(data_export!E29=0, "", data_export!E29) -> 0.0138026 | O45: =IF(data_export!F29=0, "", data_export!F29) -> -0.0064311 | P45: =IF(data_export!G29=0, "", data_export!G29) -> 1.015898 | R45: =IF(data_export!H29=0, "", data_export!H29) -> 0.003684 | S45: =IF(data_export!I29=0, "", data_export!I29) -> 1.003684 | T45: =IF(data_export!J29=0, "", data_export!J29) -> 1.012169
H46: =data_export!A30 -> HY (S-STW) | J46: =IF(data_export!B30=0, "", data_export!B30) -> 1 | K46: =IF(data_export!C30=0, "", data_export!C30) -> 0.0180959 | M46: =IF(data_export!D30=0, "", data_export!D30) -> 0.0010737 | N46: =IF(data_export!E30=0, "", data_export!E30) -> 0.0308237 | O46: =IF(data_export!F30=0, "", data_export!F30) -> -0.0142997 | P46: =IF(data_export!G30=0, "", data_export!G30) -> 1.035694 | R46: =IF(data_export!H30=0, "", data_export!H30) -> 0.0081832 | S46: =IF(data_export!I30=0, "", data_export!I30) -> 1.008183 | T46: =IF(data_export!J30=0, "", data_export!J30) -> 1.027287
H47: =data_export!A31 -> HY (F-ITC) | J47: =IF(data_export!B31=0, "", data_export!B31) -> 1 | K47: =IF(data_export!C31=0, "", data_export!C31) -> 0.0051932 | M47: =IF(data_export!D31=0, "", data_export!D31) -> 8.7e-05 | N47: =IF(data_export!E31=0, "", data_export!E31) -> 0.0087061 | O47: =IF(data_export!F31=0, "", data_export!F31) -> -0.0041038 | P47: =IF(data_export!G31=0, "", data_export!G31) -> 1.009883 | R47: =IF(data_export!H31=0, "", data_export!H31) -> 0.0023571 | S47: =IF(data_export!I31=0, "", data_export!I31) -> 1.002357 | T47: =IF(data_export!J31=0, "", data_export!J31) -> 1.007508
H48: =data_export!A32 -> HY (S-ITC) | J48: =IF(data_export!B32=0, "", data_export!B32) -> 1 | K48: =IF(data_export!C32=0, "", data_export!C32) -> 0.0011259 | M48: =IF(data_export!D32=0, "", data_export!D32) -> 4.07e-06 | N48: =IF(data_export!E32=0, "", data_export!E32) -> 0.0018782 | O48: =IF(data_export!F32=0, "", data_export!F32) -> -0.0008897 | P48: =IF(data_export!G32=0, "", data_export!G32) -> 1.002118 | R48: =IF(data_export!H32=0, "", data_export!H32) -> 0.0005116 | S48: =IF(data_export!I32=0, "", data_export!I32) -> 1.000512 | T48: =IF(data_export!J32=0, "", data_export!J32) -> 1.001606
G50: =data_export!A33 -> Weatherization | J50: =IF(data_export!B33=0, "", data_export!B33) -> 0.7740969 | K50: =IF(data_export!C33=0, "", data_export!C33) -> 0.2691714 | M50: =IF(data_export!D33=0, "", data_export!D33) | N50: =IF(data_export!E33=0, "", data_export!E33) | O50: =IF(data_export!F33=0, "", data_export!F33) -> -0.0541347 | P50: =IF(data_export!G33=0, "", data_export!G33) -> 0.9891335 | R50: =IF(data_export!H33=0, "", data_export!H33) -> 0.0117654 | S50: =IF(data_export!I33=0, "", data_export!I33) -> 1.011765 | T50: =IF(data_export!J33=0, "", data_export!J33) -> 0.9776313
H51: =data_export!A34 -> EPP | J51: =IF(data_export!B34=0, "", data_export!B34) -> 0.7500001 | K51: =IF(data_export!C34=0, "", data_export!C34) -> 0.5441011 | M51: =IF(data_export!D34=0, "", data_export!D34) | N51: =IF(data_export!E34=0, "", data_export!E34) | O51: =IF(data_export!F34=0, "", data_export!F34) -> -0.0574578 | P51: =IF(data_export!G34=0, "", data_export!G34) -> 1.236643 | R51: =IF(data_export!H34=0, "", data_export!H34) -> 0.0218937 | S51: =IF(data_export!I34=0, "", data_export!I34) -> 1.021894 | T51: =IF(data_export!J34=0, "", data_export!J34) -> 1.210149
H52: =data_export!A35 -> IHWAP | J52: =IF(data_export!B35=0, "", data_export!B35) -> 0.75 | K52: =IF(data_export!C35=0, "", data_export!C35) -> 0.3591664 | M52: =IF(data_export!D35=0, "", data_export!D35) | N52: =IF(data_export!E35=0, "", data_export!E35) | O52: =IF(data_export!F35=0, "", data_export!F35) -> -0.1105859 | P52: =IF(data_export!G35=0, "", data_export!G35) -> 0.9985805 | R52: =IF(data_export!H35=0, "", data_export!H35) -> 0.0187697 | S52: =IF(data_export!I35=0, "", data_export!I35) -> 1.01877 | T52: =IF(data_export!J35=0, "", data_export!J35) -> 0.9801827
H53: =data_export!A36 -> WI RF | J53: =IF(data_export!B36=0, "", data_export!B36) -> 0.8704846 | K53: =IF(data_export!C36=0, "", data_export!C36) -> 0.0501621 | M53: =IF(data_export!D36=0, "", data_export!D36) | N53: =IF(data_export!E36=0, "", data_export!E36) | O53: =IF(data_export!F36=0, "", data_export!F36) -> -0.0010531 | P53: =IF(data_export!G36=0, "", data_export!G36) -> 0.9195937 | R53: =IF(data_export!H36=0, "", data_export!H36) -> -0.0002387 | S53: =IF(data_export!I36=0, "", data_export!I36) -> 0.9997613 | T53: =IF(data_export!J36=0, "", data_export!J36) -> 0.9198132
H54: =data_export!A37 -> WAP | J54: =IF(data_export!B37=0, "", data_export!B37) -> 0.7500001 | K54: =IF(data_export!C37=0, "", data_export!C37) -> 0.2654865 | M54: =IF(data_export!D37=0, "", data_export!D37) | N54: =IF(data_export!E37=0, "", data_export!E37) | O54: =IF(data_export!F37=0, "", data_export!F37) -> -0.0881718 | P54: =IF(data_export!G37=0, "", data_export!G37) -> 0.9273148 | R54: =IF(data_export!H37=0, "", data_export!H37) -> 0.0132946 | S54: =IF(data_export!I37=0, "", data_export!I37) -> 1.013295 | T54: =IF(data_export!J37=0, "", data_export!J37) -> 0.9151483
H55: =data_export!A38 -> LEEP+ | J55: =IF(data_export!B38=0, "", data_export!B38) -> 0.7499999 | K55: =IF(data_export!C38=0, "", data_export!C38) -> 0.1269407 | M55: =IF(data_export!D38=0, "", data_export!D38) | N55: =IF(data_export!E38=0, "", data_export!E38) | O55: =IF(data_export!F38=0, "", data_export!F38) -> -0.0134051 | P55: =IF(data_export!G38=0, "", data_export!G38) -> 0.8635356 | R55: =IF(data_export!H38=0, "", data_export!H38) -> 0.0051079 | S55: =IF(data_export!I38=0, "", data_export!I38) -> 1.005108 | T55: =IF(data_export!J38=0, "", data_export!J38) -> 0.8591472
G57: =data_export!A39 -> Other Subsidies | J57: =IF(data_export!B39=0, "", data_export!B39) -> 0.88749 | K57: =IF(data_export!C39=0, "", data_export!C39) -> 1.694998 | M57: =IF(data_export!D39=0, "", data_export!D39) | N57: =IF(data_export!E39=0, "", data_export!E39) | O57: =IF(data_export!F39=0, "", data_export!F39) -> -0.0653731 | P57: =IF(data_export!G39=0, "", data_export!G39) -> 2.517115 | R57: =IF(data_export!H39=0, "", data_export!H39) -> 0.0101288 | S57: =IF(data_export!I39=0, "", data_export!I39) -> 1.010129 | T57: =IF(data_export!J39=0, "", data_export!J39) -> 2.491875
H58: =data_export!A40 -> CA 20/20 | J58: =IF(data_export!B40=0, "", data_export!B40) -> 0.8821229 | K58: =IF(data_export!C40=0, "", data_export!C40) -> 1.919402 | M58: =IF(data_export!D40=0, "", data_export!D40) | N58: =IF(data_export!E40=0, "", data_export!E40) | O58: =IF(data_export!F40=0, "", data_export!F40) -> -0.1307462 | P58: =IF(data_export!G40=0, "", data_export!G40) -> 2.670779 | R58: =IF(data_export!H40=0, "", data_export!H40) -> 0.0382046 | S58: =IF(data_export!I40=0, "", data_export!I40) -> 1.038205 | T58: =IF(data_export!J40=0, "", data_export!J40) -> 2.572498
H59: =data_export!A41 -> CRP | J59: =IF(data_export!B41=0, "", data_export!B41) -> 0.8928571 | K59: =IF(data_export!C41=0, "", data_export!C41) -> 1.470593 | M59: =IF(data_export!D41=0, "", data_export!D41) | N59: =IF(data_export!E41=0, "", data_export!E41) | O59: =IF(data_export!F41=0, "", data_export!F41) | P59: =IF(data_export!G41=0, "", data_export!G41) -> 2.36345 | R59: =IF(data_export!H41=0, "", data_export!H41) -> -0.017947 | S59: =IF(data_export!I41=0, "", data_export!I41) -> 0.982053 | T59: =IF(data_export!J41=0, "", data_export!J41) -> 2.406642
F61: Panel B. Nudges and Marketing
G63: =data_export!A42 -> Home Energy Reports | J63: =IF(data_export!B42=0, "", data_export!B42) | K63: =IF(data_export!C42=0, "", data_export!C42) -> 1.876076 | M63: =IF(data_export!D42=0, "", data_export!D42) | N63: =IF(data_export!E42=0, "", data_export!E42) | O63: =IF(data_export!F42=0, "", data_export!F42) -> -0.0301738 | P63: =IF(data_export!G42=0, "", data_export!G42) -> 1.845902 | R63: =IF(data_export!H42=0, "", data_export!H42) -> -0.051017 | S63: =IF(data_export!I42=0, "", data_export!I42) -> 0.948983 | T63: =IF(data_export!J42=0, "", data_export!J42) -> 1.945137
H64: =data_export!A43 -> HER (17 RCTs) | J64: =IF(data_export!B43=0, "", data_export!B43) | K64: =IF(data_export!C43=0, "", data_export!C43) -> 3.466387 | M64: =IF(data_export!D43=0, "", data_export!D43) | N64: =IF(data_export!E43=0, "", data_export!E43) | O64: =IF(data_export!F43=0, "", data_export!F43) -> -0.2442774 | P64: =IF(data_export!G43=0, "", data_export!G43) -> 3.22211 | R64: =IF(data_export!H43=0, "", data_export!H43) -> 0.071892 | S64: =IF(data_export!I43=0, "", data_export!I43) -> 1.071892 | T64: =IF(data_export!J43=0, "", data_export!J43) -> 3.006002
H65: =data_export!A44 -> Opower Elec. (166 RCTs) | J65: =IF(data_export!B44=0, "", data_export!B44) | K65: =IF(data_export!C44=0, "", data_export!C44) -> 2.906034 | M65: =IF(data_export!D44=0, "", data_export!D44) | N65: =IF(data_export!E44=0, "", data_export!E44) | O65: =IF(data_export!F44=0, "", data_export!F44) -> -0.2047891 | P65: =IF(data_export!G44=0, "", data_export!G44) -> 2.701245 | R65: =IF(data_export!H44=0, "", data_export!H44) -> 0.0602704 | S65: =IF(data_export!I44=0, "", data_export!I44) -> 1.06027 | T65: =IF(data_export!J44=0, "", data_export!J44) -> 2.547694
H66: =data_export!A45 -> PER | J66: =IF(data_export!B45=0, "", data_export!B45) | K66: =IF(data_export!C45=0, "", data_export!C45) -> 0.2935726 | M66: =IF(data_export!D45=0, "", data_export!D45) | N66: =IF(data_export!E45=0, "", data_export!E45) | O66: =IF(data_export!F45=0, "", data_export!F45) -> 0.6950432 | P66: =IF(data_export!G45=0, "", data_export!G45) -> 0.9886158 | R66: =IF(data_export!H45=0, "", data_export!H45) -> -0.382043 | S66: =IF(data_export!I45=0, "", data_export!I45) -> 0.617957 | T66: =IF(data_export!J45=0, "", data_export!J45) -> 1.599813
H67: =data_export!A46 -> Opower Nat. Gas (52 RCTs) | J67: =IF(data_export!B46=0, "", data_export!B46) | K67: =IF(data_export!C46=0, "", data_export!C46) -> 0.838311 | M67: =IF(data_export!D46=0, "", data_export!D46) | N67: =IF(data_export!E46=0, "", data_export!E46) | O67: =IF(data_export!F46=0, "", data_export!F46) -> -0.3666719 | P67: =IF(data_export!G46=0, "", data_export!G46) -> 0.4716391 | R67: =IF(data_export!H46=0, "", data_export!H46) -> 0.0458127 | S67: =IF(data_export!I46=0, "", data_export!I46) -> 1.045813 | T67: =IF(data_export!J46=0, "", data_export!J46) -> 0.4509785
G69: =data_export!A47 -> Other Nudges | J69: =IF(data_export!B47=0, "", data_export!B47) -> 0.5069134 | K69: =IF(data_export!C47=0, "", data_export!C47) -> 4.350518 | M69: =IF(data_export!D47=0, "", data_export!D47) | N69: =IF(data_export!E47=0, "", data_export!E47) | O69: =IF(data_export!F47=0, "", data_export!F47) -> -0.6589198 | P69: =IF(data_export!G47=0, "", data_export!G47) -> 4.198511 | R69: =IF(data_export!H47=0, "", data_export!H47) -> 2.166738 | S69: =IF(data_export!I47=0, "", data_export!I47) -> 3.166738 | T69: =IF(data_export!J47=0, "", data_export!J47) -> 1.325816
H70: =data_export!A48 -> Audit Nudge | J70: =IF(data_export!B48=0, "", data_export!B48) | K70: =IF(data_export!C48=0, "", data_export!C48) -> 8.049906 | M70: =IF(data_export!D48=0, "", data_export!D48) | N70: =IF(data_export!E48=0, "", data_export!E48) | O70: =IF(data_export!F48=0, "", data_export!F48) -> -0.5424074 | P70: =IF(data_export!G48=0, "", data_export!G48) -> 7.507498 | R70: =IF(data_export!H48=0, "", data_export!H48) -> 2.546548 | S70: =IF(data_export!I48=0, "", data_export!I48) -> 3.546548 | T70: =IF(data_export!J48=0, "", data_export!J48) -> 2.116847
H71: =data_export!A49 -> Solarize | J71: =IF(data_export!B49=0, "", data_export!B49) -> 1.144508 | K71: =IF(data_export!C49=0, "", data_export!C49) -> 13.52404 | M71: =IF(data_export!D49=0, "", data_export!D49) | N71: =IF(data_export!E49=0, "", data_export!E49) | O71: =IF(data_export!F49=0, "", data_export!F49) -> -1.844353 | P71: =IF(data_export!G49=0, "", data_export!G49) -> 12.8242 | R71: =IF(data_export!H49=0, "", data_export!H49) -> 6.090937 | S71: =IF(data_export!I49=0, "", data_export!I49) -> 7.090937 | T71: =IF(data_export!J49=0, "", data_export!J49) -> 1.808534
H72: =data_export!A50 -> ES (WH) + Nudge | J72: =IF(data_export!B50=0, "", data_export!B50) -> 0.4157895 | K72: =IF(data_export!C50=0, "", data_export!C50) -> 1.438654 | M72: =IF(data_export!D50=0, "", data_export!D50) | N72: =IF(data_export!E50=0, "", data_export!E50) | O72: =IF(data_export!F50=0, "", data_export!F50) -> -0.6292583 | P72: =IF(data_export!G50=0, "", data_export!G50) -> 1.225186 | R72: =IF(data_export!H50=0, "", data_export!H50) -> 0.0748746 | S72: =IF(data_export!I50=0, "", data_export!I50) -> 1.074875 | T72: =IF(data_export!J50=0, "", data_export!J50) -> 1.13984
H73: =data_export!A51 -> IHWAP + Nudge (H) | J73: =IF(data_export!B51=0, "", data_export!B51) -> 0.7386044 | K73: =IF(data_export!C51=0, "", data_export!C51) -> 0.4515422 | M73: =IF(data_export!D51=0, "", data_export!D51) | N73: =IF(data_export!E51=0, "", data_export!E51) | O73: =IF(data_export!F51=0, "", data_export!F51) -> -0.1046995 | P73: =IF(data_export!G51=0, "", data_export!G51) -> 1.085447 | R73: =IF(data_export!H51=0, "", data_export!H51) -> 0.0149803 | S73: =IF(data_export!I51=0, "", data_export!I51) -> 1.01498 | T73: =IF(data_export!J51=0, "", data_export!J51) -> 1.069427
H74: =data_export!A52 -> IHWAP + Nudge (L) | J74: =IF(data_export!B52=0, "", data_export!B52) -> 0.7425786 | K74: =IF(data_export!C52=0, "", data_export!C52) -> 0.4361615 | M74: =IF(data_export!D52=0, "", data_export!D52) | N74: =IF(data_export!E52=0, "", data_export!E52) | O74: =IF(data_export!F52=0, "", data_export!F52) -> -0.1012194 | P74: =IF(data_export!G52=0, "", data_export!G52) -> 1.077521 | R74: =IF(data_export!H52=0, "", data_export!H52) -> 0.0141693 | S74: =IF(data_export!I52=0, "", data_export!I52) -> 1.014169 | T74: =IF(data_export!J52=0, "", data_export!J52) -> 1.062466
H75: =data_export!A53 -> WAP + Nudge | J75: =IF(data_export!B53=0, "", data_export!B53) | K75: =IF(data_export!C53=0, "", data_export!C53) -> 2.202801 | M75: =IF(data_export!D53=0, "", data_export!D53) | N75: =IF(data_export!E53=0, "", data_export!E53) | O75: =IF(data_export!F53=0, "", data_export!F53) -> -0.7315806 | P75: =IF(data_export!G53=0, "", data_export!G53) -> 1.47122 | R75: =IF(data_export!H53=0, "", data_export!H53) -> 4.258919 | S75: =IF(data_export!I53=0, "", data_export!I53) -> 5.258919 | T75: =IF(data_export!J53=0, "", data_export!J53) -> 0.2797571
F77: Panel C. Revenue Raisers
G79: =data_export!A54 -> Gasoline Taxes | J79: =IF(data_export!B54=0, "", data_export!B54) -> 1 | K79: =IF(data_export!C54=0, "", data_export!C54) -> -0.4325176 | M79: =IF(data_export!D54=0, "", data_export!D54) -> -0.0002449 | N79: =IF(data_export!E54=0, "", data_export!E54) -> -0.0019331 | O79: =IF(data_export!F54=0, "", data_export!F54) -> 0.0598143 | P79: =IF(data_export!G54=0, "", data_export!G54) -> 0.6251186 | R79: =IF(data_export!H54=0, "", data_export!H54) -> -0.0690563 | S79: =IF(data_export!I54=0, "", data_export!I54) -> 0.9309437 | T79: =IF(data_export!J54=0, "", data_export!J54) -> 0.6714892
H80: =data_export!A55 -> Gas (DK) | J80: =IF(data_export!B55=0, "", data_export!B55) -> 1 | K80: =IF(data_export!C55=0, "", data_export!C55) -> -0.7075715 | M80: =IF(data_export!D55=0, "", data_export!D55) -> -0.0002449 | N80: =IF(data_export!E55=0, "", data_export!E55) -> -0.0019331 | O80: =IF(data_export!F55=0, "", data_export!F55) -> 0.0978205 | P80: =IF(data_export!G55=0, "", data_export!G55) -> 0.3880709 | R80: =IF(data_export!H55=0, "", data_export!H55) -> -0.1128245 | S80: =IF(data_export!I55=0, "", data_export!I55) -> 0.8871755 | T80: =IF(data_export!J55=0, "", data_export!J55) -> 0.437423
H81: =data_export!A56 -> Gas (Su) | J81: =IF(data_export!B56=0, "", data_export!B56) -> 1 | K81: =IF(data_export!C56=0, "", data_export!C56) -> -0.6105616 | M81: =IF(data_export!D56=0, "", data_export!D56) -> -0.0002449 | N81: =IF(data_export!E56=0, "", data_export!E56) -> -0.0019331 | O81: =IF(data_export!F56=0, "", data_export!F56) -> 0.0844159 | P81: =IF(data_export!G56=0, "", data_export!G56) -> 0.4716763 | R81: =IF(data_export!H56=0, "", data_export!H56) -> -0.0973877 | S81: =IF(data_export!I56=0, "", data_export!I56) -> 0.9026123 | T81: =IF(data_export!J56=0, "", data_export!J56) -> 0.522568
H82: =data_export!A57 -> Gas (Coglianese) | J82: =IF(data_export!B57=0, "", data_export!B57) -> 1 | K82: =IF(data_export!C57=0, "", data_export!C57) -> -0.5659062 | M82: =IF(data_export!D57=0, "", data_export!D57) -> -0.0002449 | N82: =IF(data_export!E57=0, "", data_export!E57) -> -0.0019331 | O82: =IF(data_export!F57=0, "", data_export!F57) -> 0.0782456 | P82: =IF(data_export!G57=0, "", data_export!G57) -> 0.5101613 | R82: =IF(data_export!H57=0, "", data_export!H57) -> -0.0902819 | S82: =IF(data_export!I57=0, "", data_export!I57) -> 0.9097181 | T82: =IF(data_export!J57=0, "", data_export!J57) -> 0.5607905
H83: =data_export!A58 -> Gas (Manzan) | J83: =IF(data_export!B58=0, "", data_export!B58) -> 1 | K83: =IF(data_export!C58=0, "", data_export!C58) -> -0.5458883 | M83: =IF(data_export!D58=0, "", data_export!D58) -> -0.0002449 | N83: =IF(data_export!E58=0, "", data_export!E58) -> -0.0019331 | O83: =IF(data_export!F58=0, "", data_export!F58) -> 0.0754795 | P83: =IF(data_export!G58=0, "", data_export!G58) -> 0.5274132 | R83: =IF(data_export!H58=0, "", data_export!H58) -> -0.0870965 | S83: =IF(data_export!I58=0, "", data_export!I58) -> 0.9129035 | T83: =IF(data_export!J58=0, "", data_export!J58) -> 0.5777316
H84: =data_export!A59 -> Gas (Small) | J84: =IF(data_export!B59=0, "", data_export!B59) -> 1 | K84: =IF(data_export!C59=0, "", data_export!C59) -> -0.5135517 | M84: =IF(data_export!D59=0, "", data_export!D59) -> -0.0002449 | N84: =IF(data_export!E59=0, "", data_export!E59) -> -0.0019331 | O84: =IF(data_export!F59=0, "", data_export!F59) -> 0.0710113 | P84: =IF(data_export!G59=0, "", data_export!G59) -> 0.5552816 | R84: =IF(data_export!H59=0, "", data_export!H59) -> -0.0819509 | S84: =IF(data_export!I59=0, "", data_export!I59) -> 0.9180491 | T84: =IF(data_export!J59=0, "", data_export!J59) -> 0.6048496
H85: =data_export!A60 -> Gas (Li) | J85: =IF(data_export!B60=0, "", data_export!B60) -> 1 | K85: =IF(data_export!C60=0, "", data_export!C60) -> -0.4966134 | M85: =IF(data_export!D60=0, "", data_export!D60) -> -0.0002449 | N85: =IF(data_export!E60=0, "", data_export!E60) -> -0.0019331 | O85: =IF(data_export!F60=0, "", data_export!F60) -> 0.0686709 | P85: =IF(data_export!G60=0, "", data_export!G60) -> 0.5698794 | R85: =IF(data_export!H60=0, "", data_export!H60) -> -0.0792556 | S85: =IF(data_export!I60=0, "", data_export!I60) -> 0.9207444 | T85: =IF(data_export!J60=0, "", data_export!J60) -> 0.6189333
H86: =data_export!A61 -> Gas (Levin) | J86: =IF(data_export!B61=0, "", data_export!B61) -> 1 | K86: =IF(data_export!C61=0, "", data_export!C61) -> -0.4534979 | M86: =IF(data_export!D61=0, "", data_export!D61) -> -0.0002449 | N86: =IF(data_export!E61=0, "", data_export!E61) -> -0.0019331 | O86: =IF(data_export!F61=0, "", data_export!F61) -> 0.0627133 | P86: =IF(data_export!G61=0, "", data_export!G61) -> 0.6070373 | R86: =IF(data_export!H61=0, "", data_export!H61) -> -0.0723948 | S86: =IF(data_export!I61=0, "", data_export!I61) -> 0.9276052 | T86: =IF(data_export!J61=0, "", data_export!J61) -> 0.6544135
H87: =data_export!A62 -> Gas (Sentenac-Chemin) | J87: =IF(data_export!B62=0, "", data_export!B62) -> 1 | K87: =IF(data_export!C62=0, "", data_export!C62) -> -0.4304003 | M87: =IF(data_export!D62=0, "", data_export!D62) -> -0.0002449 | N87: =IF(data_export!E62=0, "", data_export!E62) -> -0.0019331 | O87: =IF(data_export!F62=0, "", data_export!F62) -> 0.0595217 | P87: =IF(data_export!G62=0, "", data_export!G62) -> 0.6269433 | R87: =IF(data_export!H62=0, "", data_export!H62) -> -0.0687194 | S87: =IF(data_export!I62=0, "", data_export!I62) -> 0.9312806 | T87: =IF(data_export!J62=0, "", data_export!J62) -> 0.6732056
H88: =data_export!A63 -> Gas (Kilian) | J88: =IF(data_export!B63=0, "", data_export!B63) -> 1 | K88: =IF(data_export!C63=0, "", data_export!C63) -> -0.3041334 | M88: =IF(data_export!D63=0, "", data_export!D63) -> -0.0002449 | N88: =IF(data_export!E63=0, "", data_export!E63) -> -0.0019331 | O88: =IF(data_export!F63=0, "", data_export!F63) -> 0.0420745 | P88: =IF(data_export!G63=0, "", data_export!G63) -> 0.735763 | R88: =IF(data_export!H63=0, "", data_export!H63) -> -0.0486271 | S88: =IF(data_export!I63=0, "", data_export!I63) -> 0.9513729 | T88: =IF(data_export!J63=0, "", data_export!J63) -> 0.7733697
H89: =data_export!A64 -> Gas (Gelman) | J89: =IF(data_export!B64=0, "", data_export!B64) -> 1 | K89: =IF(data_export!C64=0, "", data_export!C64) -> -0.2517789 | M89: =IF(data_export!D64=0, "", data_export!D64) -> -0.0002449 | N89: =IF(data_export!E64=0, "", data_export!E64) -> -0.0019331 | O89: =IF(data_export!F64=0, "", data_export!F64) -> 0.0348403 | P89: =IF(data_export!G64=0, "", data_export!G64) -> 0.7808833 | R89: =IF(data_export!H64=0, "", data_export!H64) -> -0.0402962 | S89: =IF(data_export!I64=0, "", data_export!I64) -> 0.9597038 | T89: =IF(data_export!J64=0, "", data_export!J64) -> 0.8136711
H90: =data_export!A65 -> Gas (Park) | J90: =IF(data_export!B65=0, "", data_export!B65) -> 1 | K90: =IF(data_export!C65=0, "", data_export!C65) -> -0.2463894 | M90: =IF(data_export!D65=0, "", data_export!D65) -> -0.0002449 | N90: =IF(data_export!E65=0, "", data_export!E65) -> -0.0019331 | O90: =IF(data_export!F65=0, "", data_export!F65) -> 0.0340956 | P90: =IF(data_export!G65=0, "", data_export!G65) -> 0.7855281 | R90: =IF(data_export!H65=0, "", data_export!H65) -> -0.0394386 | S90: =IF(data_export!I65=0, "", data_export!I65) -> 0.9605614 | T90: =IF(data_export!J65=0, "", data_export!J65) -> 0.8177801
H91: =data_export!A66 -> Gas (Hughes) | J91: =IF(data_export!B66=0, "", data_export!B66) -> 1 | K91: =IF(data_export!C66=0, "", data_export!C66) -> -0.0639184 | M91: =IF(data_export!D66=0, "", data_export!D66) -> -0.0002449 | N91: =IF(data_export!E66=0, "", data_export!E66) -> -0.0019331 | O91: =IF(data_export!F66=0, "", data_export!F66) -> 0.0088822 | P91: =IF(data_export!G66=0, "", data_export!G66) -> 0.9427857 | R91: =IF(data_export!H66=0, "", data_export!H66) -> -0.0104027 | S91: =IF(data_export!I66=0, "", data_export!I66) -> 0.9895973 | T91: =IF(data_export!J66=0, "", data_export!J66) -> 0.9526964
G93: =data_export!A67 -> Other Fuel Taxes | J93: =IF(data_export!B67=0, "", data_export!B67) -> 1 | K93: =IF(data_export!C67=0, "", data_export!C67) -> -0.2506857 | M93: =IF(data_export!D67=0, "", data_export!D67) | N93: =IF(data_export!E67=0, "", data_export!E67) | O93: =IF(data_export!F67=0, "", data_export!F67) -> 0.0252733 | P93: =IF(data_export!G67=0, "", data_export!G67) -> 0.7745876 | R93: =IF(data_export!H67=0, "", data_export!H67) -> -0.0297543 | S93: =IF(data_export!I67=0, "", data_export!I67) -> 0.9702457 | T93: =IF(data_export!J67=0, "", data_export!J67) -> 0.7983416
H94: =data_export!A68 -> Jet Fuel | J94: =IF(data_export!B68=0, "", data_export!B68) -> 1 | K94: =IF(data_export!C68=0, "", data_export!C68) -> -0.3131514 | M94: =IF(data_export!D68=0, "", data_export!D68) | N94: =IF(data_export!E68=0, "", data_export!E68) | O94: =IF(data_export!F68=0, "", data_export!F68) -> 0.035554 | P94: =IF(data_export!G68=0, "", data_export!G68) -> 0.7224026 | R94: =IF(data_export!H68=0, "", data_export!H68) -> -0.0418545 | S94: =IF(data_export!I68=0, "", data_export!I68) -> 0.9581455 | T94: =IF(data_export!J68=0, "", data_export!J68) -> 0.7539592
H95: =data_export!A69 -> Diesel | J95: =IF(data_export!B69=0, "", data_export!B69) -> 1 | K95: =IF(data_export!C69=0, "", data_export!C69) -> -0.1882201 | M95: =IF(data_export!D69=0, "", data_export!D69) | N95: =IF(data_export!E69=0, "", data_export!E69) | O95: =IF(data_export!F69=0, "", data_export!F69) -> 0.0149926 | P95: =IF(data_export!G69=0, "", data_export!G69) -> 0.8267726 | R95: =IF(data_export!H69=0, "", data_export!H69) -> -0.017654 | S95: =IF(data_export!I69=0, "", data_export!I69) -> 0.982346 | T95: =IF(data_export!J69=0, "", data_export!J69) -> 0.8416307
G97: =data_export!A70 -> Other Revenue Raisers | J97: =IF(data_export!B70=0, "", data_export!B70) -> 0.9785933 | K97: =IF(data_export!C70=0, "", data_export!C70) -> -0.1514833 | M97: =IF(data_export!D70=0, "", data_export!D70) | N97: =IF(data_export!E70=0, "", data_export!E70) | O97: =IF(data_export!F70=0, "", data_export!F70) -> -0.108284 | P97: =IF(data_export!G70=0, "", data_export!G70) -> 0.718826 | R97: =IF(data_export!H70=0, "", data_export!H70) -> 0.111731 | S97: =IF(data_export!I70=0, "", data_export!I70) -> 1.111731 | T97: =IF(data_export!J70=0, "", data_export!J70) -> 0.6465826
H98: =data_export!A71 -> CPP (AJ) | J98: =IF(data_export!B71=0, "", data_export!B71) -> 1 | K98: =IF(data_export!C71=0, "", data_export!C71) -> -0.1364863 | M98: =IF(data_export!D71=0, "", data_export!D71) | N98: =IF(data_export!E71=0, "", data_export!E71) | O98: =IF(data_export!F71=0, "", data_export!F71) -> -0.3231302 | P98: =IF(data_export!G71=0, "", data_export!G71) -> 0.5403835 | R98: =IF(data_export!H71=0, "", data_export!H71) -> 0.1776144 | S98: =IF(data_export!I71=0, "", data_export!I71) -> 1.177614 | T98: =IF(data_export!J71=0, "", data_export!J71) -> 0.4588798
H99: =data_export!A72 -> CARE | J99: =IF(data_export!B72=0, "", data_export!B72) -> 0.9357799 | K99: =IF(data_export!C72=0, "", data_export!C72) -> -0.2677665 | M99: =IF(data_export!D72=0, "", data_export!D72) | N99: =IF(data_export!E72=0, "", data_export!E72) | O99: =IF(data_export!F72=0, "", data_export!F72) -> 0.1171194 | P99: =IF(data_export!G72=0, "", data_export!G72) -> 0.7851327 | R99: =IF(data_export!H72=0, "", data_export!H72) -> 0.0922555 | S99: =IF(data_export!I72=0, "", data_export!I72) -> 1.092256 | T99: =IF(data_export!J72=0, "", data_export!J72) -> 0.7188178
H100: =data_export!A73 -> CPP (PJ) | J100: =IF(data_export!B73=0, "", data_export!B73) -> 1 | K100: =IF(data_export!C73=0, "", data_export!C73) -> -0.0501971 | M100: =IF(data_export!D73=0, "", data_export!D73) | N100: =IF(data_export!E73=0, "", data_export!E73) | O100: =IF(data_export!F73=0, "", data_export!F73) -> -0.1188412 | P100: =IF(data_export!G73=0, "", data_export!G73) -> 0.8309617 | R100: =IF(data_export!H73=0, "", data_export!H73) -> 0.0653232 | S100: =IF(data_export!I73=0, "", data_export!I73) -> 1.065323 | T100: =IF(data_export!J73=0, "", data_export!J73) -> 0.780009
G102: =data_export!A74 -> Cap and Trade | J102: =IF(data_export!B74=0, "", data_export!B74) -> 1 | K102: =IF(data_export!C74=0, "", data_export!C74) -> -0.8543289 | M102: =IF(data_export!D74=0, "", data_export!D74) | N102: =IF(data_export!E74=0, "", data_export!E74) | O102: =IF(data_export!F74=0, "", data_export!F74) | P102: =IF(data_export!G74=0, "", data_export!G74) -> 0.1456711 | R102: =IF(data_export!H74=0, "", data_export!H74) -> -0.0208201 | S102: =IF(data_export!I74=0, "", data_export!I74) -> 0.9791799 | T102: =IF(data_export!J74=0, "", data_export!J74) -> 0.1487685
H103: =data_export!A75 -> RGGI | J103: =IF(data_export!B75=0, "", data_export!B75) -> 1 | K103: =IF(data_export!C75=0, "", data_export!C75) -> -1.646022 | M103: =IF(data_export!D75=0, "", data_export!D75) | N103: =IF(data_export!E75=0, "", data_export!E75) | O103: =IF(data_export!F75=0, "", data_export!F75) | P103: =IF(data_export!G75=0, "", data_export!G75) -> -0.646022 | R103: =IF(data_export!H75=0, "", data_export!H75) -> -0.0373127 | S103: =IF(data_export!I75=0, "", data_export!I75) -> 0.9626873 | T103: =IF(data_export!J75=0, "", data_export!J75) -> -0.6710612
H104: =data_export!A76 -> CA CT | J104: =IF(data_export!B76=0, "", data_export!B76) -> 1 | K104: =IF(data_export!C76=0, "", data_export!C76) -> -0.0626358 | M104: =IF(data_export!D76=0, "", data_export!D76) | N104: =IF(data_export!E76=0, "", data_export!E76) | O104: =IF(data_export!F76=0, "", data_export!F76) | P104: =IF(data_export!G76=0, "", data_export!G76) -> 0.9373642 | R104: =IF(data_export!H76=0, "", data_export!H76) -> -0.0043275 | S104: =IF(data_export!I76=0, "", data_export!I76) -> 0.9956725 | T104: =IF(data_export!J76=0, "", data_export!J76) -> 0.9414383
F106: Panel D. International
G108: =data_export!A77 -> Cookstoves | J108: =IF(data_export!B77=0, "", data_export!B77) -> 4.100581 | K108: =IF(data_export!C77=0, "", data_export!C77) -> 20.10259 | M108: =IF(data_export!D77=0, "", data_export!D77) | N108: =IF(data_export!E77=0, "", data_export!E77) | O108: =IF(data_export!F77=0, "", data_export!F77) | P108: =IF(data_export!G77=0, "", data_export!G77) -> 24.20317 | R108: =IF(data_export!H77=0, "", data_export!H77) -> -0.3925851 | S108: =IF(data_export!I77=0, "", data_export!I77) -> 0.6074149 | T108: =IF(data_export!J77=0, "", data_export!J77) -> 39.8462
H109: =data_export!A78 -> Cookstove (Kenya) | J109: =IF(data_export!B78=0, "", data_export!B78) -> 7.655874 | K109: =IF(data_export!C78=0, "", data_export!C78) -> 43.16091 | M109: =IF(data_export!D78=0, "", data_export!D78) | N109: =IF(data_export!E78=0, "", data_export!E78) | O109: =IF(data_export!F78=0, "", data_export!F78) | P109: =IF(data_export!G78=0, "", data_export!G78) -> 50.81678 | R109: =IF(data_export!H78=0, "", data_export!H78) -> -0.8428928 | S109: =IF(data_export!I78=0, "", data_export!I78) -> 0.1571072 | T109: =IF(data_export!J78=0, "", data_export!J78) -> 323.4529
H110: =data_export!A79 -> Cookstove (India) | J110: =IF(data_export!B79=0, "", data_export!B79) -> 0.545288 | K110: =IF(data_export!C79=0, "", data_export!C79) -> -2.955725 | M110: =IF(data_export!D79=0, "", data_export!D79) | N110: =IF(data_export!E79=0, "", data_export!E79) | O110: =IF(data_export!F79=0, "", data_export!F79) | P110: =IF(data_export!G79=0, "", data_export!G79) -> -2.410437 | R110: =IF(data_export!H79=0, "", data_export!H79) -> 0.0577226 | S110: =IF(data_export!I79=0, "", data_export!I79) -> 1.057723 | T110: =IF(data_export!J79=0, "", data_export!J79) -> -2.278893
G112: =data_export!A80 -> Deforestation | J112: =IF(data_export!B80=0, "", data_export!B80) -> 0.461879 | K112: =IF(data_export!C80=0, "", data_export!C80) -> 14.44322 | M112: =IF(data_export!D80=0, "", data_export!D80) | N112: =IF(data_export!E80=0, "", data_export!E80) | O112: =IF(data_export!F80=0, "", data_export!F80) | P112: =IF(data_export!G80=0, "", data_export!G80) -> 14.9051 | R112: =IF(data_export!H80=0, "", data_export!H80) -> -0.2820627 | S112: =IF(data_export!I80=0, "", data_export!I80) -> 0.7179372 | T112: =IF(data_export!J80=0, "", data_export!J80) -> 20.761
H113: =data_export!A81 -> REDD+ (SL) | J113: =IF(data_export!B81=0, "", data_export!B81) | K113: =IF(data_export!C81=0, "", data_export!C81) -> 35.84024 | M113: =IF(data_export!D81=0, "", data_export!D81) | N113: =IF(data_export!E81=0, "", data_export!E81) | O113: =IF(data_export!F81=0, "", data_export!F81) | P113: =IF(data_export!G81=0, "", data_export!G81) -> 35.84024 | R113: =IF(data_export!H81=0, "", data_export!H81) -> -0.6999269 | S113: =IF(data_export!I81=0, "", data_export!I81) -> 0.3000731 | T113: =IF(data_export!J81=0, "", data_export!J81) -> 119.4383
H114: =data_export!A82 -> Deforest (Uganda) | J114: =IF(data_export!B82=0, "", data_export!B82) -> 0.420637 | K114: =IF(data_export!C82=0, "", data_export!C82) -> 4.537994 | M114: =IF(data_export!D82=0, "", data_export!D82) | N114: =IF(data_export!E82=0, "", data_export!E82) | O114: =IF(data_export!F82=0, "", data_export!F82) | P114: =IF(data_export!G82=0, "", data_export!G82) -> 4.958631 | R114: =IF(data_export!H82=0, "", data_export!H82) -> -0.0886228 | S114: =IF(data_export!I82=0, "", data_export!I82) -> 0.9113771 | T114: =IF(data_export!J82=0, "", data_export!J82) -> 5.440811
H115: =data_export!A83 -> REDD+ | J115: =IF(data_export!B83=0, "", data_export!B83) -> 0.965 | K115: =IF(data_export!C83=0, "", data_export!C83) -> 2.951421 | M115: =IF(data_export!D83=0, "", data_export!D83) | N115: =IF(data_export!E83=0, "", data_export!E83) | O115: =IF(data_export!F83=0, "", data_export!F83) | P115: =IF(data_export!G83=0, "", data_export!G83) -> 3.916421 | R115: =IF(data_export!H83=0, "", data_export!H83) -> -0.0576385 | S115: =IF(data_export!I83=0, "", data_export!I83) -> 0.9423615 | T115: =IF(data_export!J83=0, "", data_export!J83) -> 4.155965
G117: =data_export!A84 -> Rice Burning | J117: =IF(data_export!B84=0, "", data_export!B84) -> 0.9437336 | K117: =IF(data_export!C84=0, "", data_export!C84) -> 9.384908 | M117: =IF(data_export!D84=0, "", data_export!D84) | N117: =IF(data_export!E84=0, "", data_export!E84) | O117: =IF(data_export!F84=0, "", data_export!F84) | P117: =IF(data_export!G84=0, "", data_export!G84) -> 10.32864 | R117: =IF(data_export!H84=0, "", data_export!H84) -> -0.1832786 | S117: =IF(data_export!I84=0, "", data_export!I84) -> 0.8167214 | T117: =IF(data_export!J84=0, "", data_export!J84) -> 12.64647
H118: =data_export!A85 -> India PES (Upfront) | J118: =IF(data_export!B85=0, "", data_export!B85) -> 0.972213 | K118: =IF(data_export!C85=0, "", data_export!C85) -> 10.64214 | M118: =IF(data_export!D85=0, "", data_export!D85) | N118: =IF(data_export!E85=0, "", data_export!E85) | O118: =IF(data_export!F85=0, "", data_export!F85) | P118: =IF(data_export!G85=0, "", data_export!G85) -> 11.61436 | R118: =IF(data_export!H85=0, "", data_export!H85) -> -0.2078313 | S118: =IF(data_export!I85=0, "", data_export!I85) -> 0.7921687 | T118: =IF(data_export!J85=0, "", data_export!J85) -> 14.66147
H119: =data_export!A86 -> India PES (Standard) | J119: =IF(data_export!B86=0, "", data_export!B86) -> 0.9152543 | K119: =IF(data_export!C86=0, "", data_export!C86) -> 8.127671 | M119: =IF(data_export!D86=0, "", data_export!D86) | N119: =IF(data_export!E86=0, "", data_export!E86) | O119: =IF(data_export!F86=0, "", data_export!F86) | P119: =IF(data_export!G86=0, "", data_export!G86) -> 9.042925 | R119: =IF(data_export!H86=0, "", data_export!H86) -> -0.1587259 | S119: =IF(data_export!I86=0, "", data_export!I86) -> 0.8412741 | T119: =IF(data_export!J86=0, "", data_export!J86) -> 10.74908
G121: =data_export!A87 -> Wind Offset | J121: =IF(data_export!B87=0, "", data_export!B87) -> 1 | K121: =IF(data_export!C87=0, "", data_export!C87) -> 7.49467 | M121: =IF(data_export!D87=0, "", data_export!D87) | N121: =IF(data_export!E87=0, "", data_export!E87) | O121: =IF(data_export!F87=0, "", data_export!F87) | P121: =IF(data_export!G87=0, "", data_export!G87) -> 8.49467 | R121: =IF(data_export!H87=0, "", data_export!H87) -> 0.1116974 | S121: =IF(data_export!I87=0, "", data_export!I87) -> 1.111697 | T121: =IF(data_export!J87=0, "", data_export!J87) -> 7.641171
H122: =data_export!A88 -> Offset (India) | J122: =IF(data_export!B88=0, "", data_export!B88) -> 1 | K122: =IF(data_export!C88=0, "", data_export!C88) -> 7.49467 | M122: =IF(data_export!D88=0, "", data_export!D88) | N122: =IF(data_export!E88=0, "", data_export!E88) | O122: =IF(data_export!F88=0, "", data_export!F88) | P122: =IF(data_export!G88=0, "", data_export!G88) -> 8.49467 | R122: =IF(data_export!H88=0, "", data_export!H88) -> 0.1116974 | S122: =IF(data_export!I88=0, "", data_export!I88) -> 1.111697 | T122: =IF(data_export!J88=0, "", data_export!J88) -> 7.641171
G124: =data_export!A89 -> International Rebates | J124: =IF(data_export!B89=0, "", data_export!B89) -> 0.6666667 | K124: =IF(data_export!C89=0, "", data_export!C89) -> -0.0175587 | M124: =IF(data_export!D89=0, "", data_export!D89) | N124: =IF(data_export!E89=0, "", data_export!E89) | O124: =IF(data_export!F89=0, "", data_export!F89) | P124: =IF(data_export!G89=0, "", data_export!G89) -> 0.649108 | R124: =IF(data_export!H89=0, "", data_export!H89) -> 0.0003429 | S124: =IF(data_export!I89=0, "", data_export!I89) -> 1.000343 | T124: =IF(data_export!J89=0, "", data_export!J89) -> 0.6488855
H125: =data_export!A90 -> Fridge (Mexico) | J125: =IF(data_export!B90=0, "", data_export!B90) -> 0.75 | K125: =IF(data_export!C90=0, "", data_export!C90) -> 0.1003563 | M125: =IF(data_export!D90=0, "", data_export!D90) | N125: =IF(data_export!E90=0, "", data_export!E90) | O125: =IF(data_export!F90=0, "", data_export!F90) | P125: =IF(data_export!G90=0, "", data_export!G90) -> 0.8503563 | R125: =IF(data_export!H90=0, "", data_export!H90) -> -0.0019599 | S125: =IF(data_export!I90=0, "", data_export!I90) -> 0.9980401 | T125: =IF(data_export!J90=0, "", data_export!J90) -> 0.8520262
H126: =data_export!A91 -> AC (Mexico) | J126: =IF(data_export!B91=0, "", data_export!B91) -> 0.75 | K126: =IF(data_export!C91=0, "", data_export!C91) -> -0.0754901 | M126: =IF(data_export!D91=0, "", data_export!D91) | N126: =IF(data_export!E91=0, "", data_export!E91) | O126: =IF(data_export!F91=0, "", data_export!F91) | P126: =IF(data_export!G91=0, "", data_export!G91) -> 0.6745098 | R126: =IF(data_export!H91=0, "", data_export!H91) -> 0.0014743 | S126: =IF(data_export!I91=0, "", data_export!I91) -> 1.001474 | T126: =IF(data_export!J91=0, "", data_export!J91) -> 0.6735169
H127: =data_export!A92 -> WAP (Mexico) | J127: =IF(data_export!B92=0, "", data_export!B92) -> 0.5 | K127: =IF(data_export!C92=0, "", data_export!C92) -> -0.0775422 | M127: =IF(data_export!D92=0, "", data_export!D92) | N127: =IF(data_export!E92=0, "", data_export!E92) | O127: =IF(data_export!F92=0, "", data_export!F92) | P127: =IF(data_export!G92=0, "", data_export!G92) -> 0.4224578 | R127: =IF(data_export!H92=0, "", data_export!H92) -> 0.0015143 | S127: =IF(data_export!I92=0, "", data_export!I92) -> 1.001514 | T127: =IF(data_export!J92=0, "", data_export!J92) -> 0.421819
